__init__.py
cron_log/__init__.py
cron_log/expressions.py
cron_log/fields.py
cron_log/handlers.py
cron_log/trigger.py
cron_log/util.py
cron_log-1.0.2.dist-info/LICENSE
cron_log-1.0.2.dist-info/METADATA
cron_log-1.0.2.dist-info/WHEEL
cron_log-1.0.2.dist-info/entry_points.txt
cron_log-1.0.2.dist-info/top_level.txt
cron_log-1.0.2.dist-info/RECORD
