Metadata-Version: 2.1
Name: cron-log
Version: 1.0.2
Summary: cron logging
Author-email: hpcm <hpcm@foxmail.com>
Maintainer-email: hpcm <hpcm@foxmail.com>
License: MIT License
Project-URL: homepage, https://github.com/HPCMCN
Project-URL: documentation, https://github.com/HPCMCN
Project-URL: repository, https://github.com/HPCMCN/cron-log
Project-URL: changelog, https://github.com/HPCMCN/cron-log
Keywords: logging,cron
Classifier: Operating System :: Microsoft :: Windows
Classifier: Operating System :: Unix
Classifier: License :: OSI Approved :: MIT License
Classifier: Operating System :: OS Independent
Classifier: Programming Language :: Python
Classifier: Programming Language :: Python :: 3
Classifier: Programming Language :: Python :: 3.6
Classifier: Programming Language :: Python :: 3.7
Classifier: Programming Language :: Python :: 3.8
Classifier: Programming Language :: Python :: 3.9
Classifier: Programming Language :: Python :: 3.10
Classifier: Programming Language :: Python :: 3 :: Only
Classifier: Programming Language :: Python :: Implementation :: CPython
Classifier: Programming Language :: Python :: Implementation :: PyPy
Requires-Python: >=3.4
License-File: LICENSE
Provides-Extra: cli
Requires-Dist: rich ; extra == 'cli'
Requires-Dist: click ; extra == 'cli'
Provides-Extra: gui
Requires-Dist: PyQt5 ; extra == 'gui'
